{ "data": [
    {
        "category":"sport_and_leisure",
        "id":"622a1c367cc59eab6f9500ae",
        "correctAnswer":"Arnold Schwarzenegger",
        "incorrectAnswers":[
            "Johnny Depp",
            "Harrison Ford",
            "Tom Cruise"
        ],
        "question":{
            "text":"What is the name of this actor?"
        },
        "tags":[
            "games",
            "words",
            "sport"
        ],
        "type":"text_choice",
        "difficulty":"medium",
        "regions":[
            
        ],
        "isNiche":false,
        "image": "assets/images/arnoldschwarzenegger.jpg"
    },
    {
        "category":"sport_and_leisure",
        "id":"622a1c367cc59eab6f950049",
        "correctAnswer":"Brad Pitt",
        "incorrectAnswers":[
            "Leonardo DiCaprio",
            "Chris Hemsworth",
            "Robert Downey Jr."
        ],
        "question":{
            "text":"What is the name of this actor?"
        },
        "tags":[
            "general_knowledge",
            "sport"
        ],
        "type":"text_choice",
        "difficulty":"medium",
        "regions":[
            
        ],
        "isNiche":false,
        "image": "assets/images/bradpitt.jpg"
    },
    {
        "category":"sport_and_leisure",
        "id":"6384b43383dddfb71ee5e364",
        "correctAnswer":"Bruce Willis",
        "incorrectAnswers":[
            "Tom Cruise",
            "Chris Hemsworth",
            "Harrison Ford"
        ],
        "question":{
            "text":"What is the name of this actor?"
        },
        "tags":[
            "sport"
        ],
        "type":"text_choice",
        "difficulty":"medium",
        "regions":[
            
        ],
        "isNiche":false,
        "image": "assets/images/brucewillis.jpg"
    },
    {
        "category":"sport_and_leisure",
        "id":"622a1c347cc59eab6f94f858",
        "correctAnswer":"Chris Hemsworth",
        "incorrectAnswers":[
            "Johnny Depp",
            "Tom Cruise",
            "Harrison Ford"
        ],
        "question":{
            "text":"What is the name of this actor?"
        },
        "tags":[
            "people",
            "sport"
        ],
        "type":"text_choice",
        "difficulty":"hard",
        "regions":[
            
        ],
        "isNiche":false,
        "image": "assets/images/chrishemsworth.jpg"
    },
    {
        "category":"sport_and_leisure",
        "id":"622a1c347cc59eab6f94f85d",
        "correctAnswer":"Harrison Ford",
        "incorrectAnswers":[
            "Leonardo DiCaprio",
            "Tom Cruise",
            "Robert Downey Jr."
        ],
        "question":{
            "text":"What is the name of this actor?"
        },
        "tags":[
            "people",
            "sport"
        ],
        "type":"text_choice",
        "difficulty":"hard",
        "regions":[
            
        ],
        "isNiche":false,
        "image": "assets/images/harrisonford.jpg"
    },
    {
        "category":"sport_and_leisure",
        "id":"622a1c367cc59eab6f950093",
        "correctAnswer":"Jennifer Lawrence",
        "incorrectAnswers":[
            "Natalie Portman",
            "Margot Robbie",
            "Angelina Jolie"
        ],
        "question":{
            "text":"What is the name of this actress?"
        },
        "tags":[
            "usa",
            "general_knowledge",
            "sport"
        ],
        "type":"text_choice",
        "difficulty":"medium",
        "regions":[
            
        ],
        "isNiche":false,
        "image": "assets/images/jenniferlawrence.jpg"
    },
    {
        "category":"sport_and_leisure",
        "id":"62417cde0f96c4efe8d7738d",
        "correctAnswer":"Johnny Depp",
        "incorrectAnswers":[
            "Leonardo DiCaprio",
            "Robert Downey Jr.",
            "Chris Hemsworth"
        ],
        "question":{
            "text":"What is the name of this actor?"
        },
        "tags":[
            "sport"
        ],
        "type":"text_choice",
        "difficulty":"hard",
        "regions":[
            
        ],
        "isNiche":false,
        "image": "assets/images/johnnydepp.jpg"
    },
    {
        "category":"sport_and_leisure",
        "id":"646262c1ab138b829b81ea5a",
        "correctAnswer":"Leonardo DiCaprio",
        "incorrectAnswers":[
            "Will Smith",
            "Chris Hemsworth",
            "Robert Downey Jr."
        ],
        "question":{
            "text":"What is the name of this actor?"
        },
        "tags":[
            "baseball",
            "sport"
        ],
        "type":"text_choice",
        "difficulty":"medium",
        "regions":[
            
        ],
        "isNiche":false,
        "image": "assets/images/leonardodicaprio.jpg"
    },
    {
        "category":"sport_and_leisure",
        "id":"645cb162602ff42ca52fb43f",
        "correctAnswer":"Morgan Freeman",
        "incorrectAnswers":[
            "Samuel L. Jackson",
            "Will Smith",
            "Brad Pitt"
        ],
        "question":{
            "text":"What is the name of this actor?"
        },
        "tags":[
            "gymnastics",
            "olympics",
            "sport"
        ],
        "type":"text_choice",
        "difficulty":"hard",
        "regions":[
            
        ],
        "isNiche":true,
        "image": "assets/images/morganfreeman.jpg"
    },
    {
        "category":"sport_and_leisure",
        "id":"622a1c347cc59eab6f94f85c",
        "correctAnswer":"Natalie Portman",
        "incorrectAnswers":[
            "Jennifer Lawrence",
            "Margot Robbie",
            "Angelina Jolie"
        ],
        "question":{
            "text":"What is the name of this actor?"
        },
        "tags":[
            "football",
            "people",
            "soccer",
            "uk",
            "sport"
        ],
        "type":"text_choice",
        "difficulty":"medium",
        "regions":[
            
        ],
        "isNiche":false,
        "image": "assets/images/natalieportman.jpg"
    },
    {
        "category":"sport_and_leisure",
        "id":"62399f03af96521963a08711",
        "correctAnswer":"Robert Downey Jr.",
        "incorrectAnswers":[
            "Johnny Depp",
            "Harrison Ford",
            "Tom Cruise"
        ],
        "question":{
            "text":"What is the name of this actor?"
        },
        "tags":[
            "world_cup",
            "football",
            "soccer",
            "sport"
        ],
        "type":"text_choice",
        "difficulty":"hard",
        "regions":[
            
        ],
        "isNiche":false,
        "image": "assets/images/robertdowneyjr.jpg"
    },
    {
        "category":"sport_and_leisure",
        "id":"62399f011437c7031fbe41d3",
        "correctAnswer":"Samuel L. Jackson",
        "incorrectAnswers":[
            "Morgan Freeman",
            "Will Smith",
            "Brad Pitt"
        ],
        "question":{
            "text":"What is the name of this actor?"
        },
        "tags":[
            "sport"
        ],
        "type":"text_choice",
        "difficulty":"hard",
        "regions":[
            
        ],
        "isNiche":false,
        "image": "assets/images/samueljackson.jpg"
    },
    {
        "category":"sport_and_leisure",
        "id":"622a1c347cc59eab6f94f887",
        "correctAnswer":"Tom Cruise",
        "incorrectAnswers":[
            "Leonardo DiCaprio",
            "Chris Hemsworth",
            "Robert Downey Jr."
        ],
        "question":{
            "text":"What is the name of this actor?"
        },
        "tags":[
            "people",
            "general_knowledge",
            "sport"
        ],
        "type":"text_choice",
        "difficulty":"easy",
        "regions":[
            
        ],
        "isNiche":false,
        "image": "assets/images/tomcruise.jpg"
    },
    {
        "category":"sport_and_leisure",
        "id":"622a1c347cc59eab6f94f887",
        "correctAnswer":"Will Smith",
        "incorrectAnswers":[
            "Leonardo DiCaprio",
            "Brad Pitt",
            "Robert Downey Jr."
        ],
        "question":{
            "text":"What is the name of this actor?"
        },
        "tags":[
            "people",
            "general_knowledge",
            "sport"
        ],
        "type":"text_choice",
        "difficulty":"easy",
        "regions":[
            
        ],
        "isNiche":false,
        "image": "assets/images/willsmith.jpg"
    }
]}